stones/__init__.py
stones/__version__.py
stones/base.py
stones/exceptions.py
stones/lmdb.py
stones/memory.py
stones/serialize.py
stones/util.py
stones_custom-0.2.1.dist-info/LICENSE
stones_custom-0.2.1.dist-info/METADATA
stones_custom-0.2.1.dist-info/WHEEL
stones_custom-0.2.1.dist-info/RECORD
