Metadata-Version: 2.1
Name: stones-custom
Version: 0.2.1
Summary: Library for Persistent key-value containers, compatible with Python dict
Home-page: https://github.com/croqaz/Stones
License: MIT
Author: Cristi Constantin
Requires-Python: >=3.9,<=4.0
Classifier: Development Status :: 4 - Beta
Classifier: Environment :: Console
Classifier: Intended Audience :: Developers
Classifier: License :: OSI Approved :: MIT License
Classifier: Natural Language :: English
Classifier: Operating System :: OS Independent
Classifier: Programming Language :: Python :: 3
Classifier: Programming Language :: Python :: 3.9
Classifier: Programming Language :: Python :: 3.10
Classifier: Programming Language :: Python :: 3.11
Classifier: Programming Language :: Python :: 3.12
Classifier: Programming Language :: Python :: 3 :: Only
Classifier: Topic :: Database
Classifier: Topic :: Software Development
Requires-Dist: lmdb (==1.4)
Project-URL: Repository, https://github.com/croqaz/Stones
